mnns/__init__.py
mnns/calculations.py
mnns/dynamics.py
mnns/fromtext.py
mnns/line_functions.py
mnns/models.py
mnns/nanowire_network.py
mnns/nanowires.py
mnns/plotting.py
mnns/typing.py
mnns/units.py
mnns/version.py
mnns-1.0.4.dist-info/licenses/LICENSE
mnns-1.0.4.dist-info/METADATA
mnns-1.0.4.dist-info/WHEEL
mnns-1.0.4.dist-info/top_level.txt
mnns-1.0.4.dist-info/RECORD
