Metadata-Version: 2.4
Name: mnns
Version: 1.0.4
Summary: Modelling and analyzing random nanowire networks in Python.
Author-email: Marcus Kasdorf <marcus.kasdorf@ucalgary.ca>
License:                     GNU GENERAL PUBLIC LICENSE
Project-URL: Source, https://github.com/marcus-k/MemNNetSim
Requires-Python: >=3.10
License-File: LICENSE
Requires-Dist: matplotlib>=3.8.4
Requires-Dist: networkx>=3.1
Requires-Dist: numpy>=1.26.4
Requires-Dist: scipy>=1.13.0
Requires-Dist: Shapely<3,>=2.0.4
Provides-Extra: dev
Requires-Dist: pytest; extra == "dev"
Requires-Dist: ipykernel; extra == "dev"
Requires-Dist: joblib; extra == "dev"
Requires-Dist: line_profiler; extra == "dev"
Requires-Dist: black; extra == "dev"
Provides-Extra: docs
Requires-Dist: mkdocs; extra == "docs"
Requires-Dist: mkdocstrings[python]; extra == "docs"
Requires-Dist: mkdocs-material; extra == "docs"
Requires-Dist: mkdocs-api-autonav; extra == "docs"
Requires-Dist: mkdocs-macros-plugin; extra == "docs"
Requires-Dist: black; extra == "docs"
Dynamic: license-file
